streamlit_arcgis_map/__init__.py
streamlit_arcgis_map/example.py
streamlit_arcgis_map/frontend/build/asset-manifest.json
streamlit_arcgis_map/frontend/build/bootstrap.min.css
streamlit_arcgis_map/frontend/build/index.html
streamlit_arcgis_map/frontend/build/static/js/1014.23d03750.chunk.js
streamlit_arcgis_map/frontend/build/static/js/1014.23d03750.chunk.js.map
streamlit_arcgis_map/frontend/build/static/js/1069.3b2df9cf.chunk.js
streamlit_arcgis_map/frontend/build/static/js/1069.3b2df9cf.chunk.js.map
streamlit_arcgis_map/frontend/build/static/js/1104.475c2381.chunk.js
streamlit_arcgis_map/frontend/build/static/js/1104.475c2381.chunk.js.LICENSE.txt
streamlit_arcgis_map/frontend/build/static/js/1104.475c2381.chunk.js.map
streamlit_arcgis_map/frontend/build/static/js/1109.e64b566b.chunk.js
streamlit_arcgis_map/frontend/build/static/js/1145.d21d70cb.chunk.js
streamlit_arcgis_map/frontend/build/static/js/1145.d21d70cb.chunk.js.map
streamlit_arcgis_map/frontend/build/static/js/1167.83f36781.chunk.js
streamlit_arcgis_map/frontend/build/static/js/1167.83f36781.chunk.js.map
streamlit_arcgis_map/frontend/build/static/js/117.5a3788e9.chunk.js
streamlit_arcgis_map/frontend/build/static/js/117.5a3788e9.chunk.js.map
streamlit_arcgis_map/frontend/build/static/js/1174.d14d04cf.chunk.js
streamlit_arcgis_map/frontend/build/static/js/1174.d14d04cf.chunk.js.map
streamlit_arcgis_map/frontend/build/static/js/1257.d0543b1e.chunk.js
streamlit_arcgis_map/frontend/build/static/js/1257.d0543b1e.chunk.js.map
streamlit_arcgis_map/frontend/build/static/js/1297.4255b95a.chunk.js
streamlit_arcgis_map/frontend/build/static/js/1297.4255b95a.chunk.js.map
streamlit_arcgis_map/frontend/build/static/js/1301.482b6d62.chunk.js
streamlit_arcgis_map/frontend/build/static/js/1301.482b6d62.chunk.js.map
streamlit_arcgis_map/frontend/build/static/js/1316.fa47cb34.chunk.js
streamlit_arcgis_map/frontend/build/static/js/1316.fa47cb34.chunk.js.map
streamlit_arcgis_map-0.0.14.dist-info/LICENSE
streamlit_arcgis_map-0.0.14.dist-info/METADATA
streamlit_arcgis_map-0.0.14.dist-info/WHEEL
streamlit_arcgis_map-0.0.14.dist-info/top_level.txt
streamlit_arcgis_map-0.0.14.dist-info/RECORD
