Metadata-Version: 2.1
Name: streamlit-arcgis-map
Version: 0.0.14
Summary: Streamlit component that allows you to visualize an arcgis map with layers and data
Home-page: 
Author: Dimitrios Iliadis
Author-email: dimitrios.iliadis@worldforestid.org
Requires-Python: >=3.7
License-File: LICENSE
Requires-Dist: streamlit >=0.63
Provides-Extra: devel
Requires-Dist: wheel ; extra == 'devel'
Requires-Dist: pytest ==7.4.0 ; extra == 'devel'
Requires-Dist: playwright ==1.39.0 ; extra == 'devel'
Requires-Dist: requests ==2.31.0 ; extra == 'devel'
Requires-Dist: pytest-playwright-snapshot ==1.0 ; extra == 'devel'
Requires-Dist: pytest-rerunfailures ==12.0 ; extra == 'devel'
